cashfree_payment/__init__.py
cashfree_payment-0.1.2.dist-info/licenses/LICENSE
cashfree_payment-0.1.2.dist-info/METADATA
cashfree_payment-0.1.2.dist-info/WHEEL
cashfree_payment-0.1.2.dist-info/top_level.txt
cashfree_payment-0.1.2.dist-info/RECORD
