Metadata-Version: 2.4
Name: cashfree-payment
Version: 0.1.2
Summary: A Python library for Cashfree payment integration with access key management
Author-email: Your Name <your.email@example.com>
License-Expression: MIT
Project-URL: Homepage, https://github.com/yourusername/cashfree-payment
Project-URL: Repository, https://github.com/yourusername/cashfree-payment
Project-URL: Issues, https://github.com/yourusername/cashfree-payment/issues
Keywords: cashfree,payment,upi,india,payment-gateway
Classifier: Development Status :: 4 - Beta
Classifier: Intended Audience :: Developers
Classifier: Programming Language :: Python :: 3
Classifier: Programming Language :: Python :: 3.8
Classifier: Programming Language :: Python :: 3.9
Classifier: Programming Language :: Python :: 3.10
Classifier: Programming Language :: Python :: 3.11
Classifier: Programming Language :: Python :: 3.12
Classifier: Topic :: Software Development :: Libraries :: Python Modules
Classifier: Topic :: Office/Business :: Financial :: Point-Of-Sale
Requires-Python: >=3.8
License-File: LICENSE
Requires-Dist: requests>=2.28.0
Requires-Dist: bcrypt>=4.0.0
Requires-Dist: flask>=3.0.3
Requires-Dist: psycopg2-binary>=2.9.10
Provides-Extra: postgres
Requires-Dist: psycopg2-binary>=2.9.0; extra == "postgres"
Provides-Extra: dev
Requires-Dist: pytest>=7.0; extra == "dev"
Requires-Dist: build; extra == "dev"
Requires-Dist: twine; extra == "dev"
Dynamic: license-file
